{
  "$schema": "../model.schema.json",
  "id": 110,
  "name": "US_FV15",
  "capabilities": {
    "interest": true,
    "inflation": true,
    "outputgap": true,
    "output": true,
    "mp_shock": true,
    "fiscal_shock": true,
    "rules": [
      3,
      4,
      5,
      6,
      7,
      8,
      9,
      10,
      11
    ]
  },
  "description": {
    "ac_ref": "Fernández-Villaverde et al. (2015) (b)",
    "paper_title": "Estimating dynamic equilibrium models with stochastic volatility",
    "journal": "Journal of Econometrics 185 (1), 216-229",
    "replicants_name": "Philipp Lieberknecht",
    "pub_date": "2015",
    "keywords": [],
    "description": "",
    "category": "Estimated US model",
    "authors": [
      "Fernández-Villaverde, Jesús",
      "Guerrón-Quintana, Pablo",
      "Rubio-Ramírez, Juan"
    ]
  },
  "msr": null,
  "variabledim": 1,
  "al": false,
  "vars": [
    "epsd",
    "epsphi",
    "epsmu_I",
    "epsA",
    "ud",
    "uphi",
    "umu",
    "uA",
    "um",
    "epspi",
    "interest_"
  ]
}